{"container_type": "Author", "filled": ["basics", "publications", "indices", "counts"], "scholar_id": "eZvfNC8AAAAJ", "source": "AUTHOR_PROFILE_PAGE", "name": "Shuang Sun", "affiliation": "Renmin University of China", "organization": 15943286154555055968, "interests": [], "email_domain": "@ruc.edu.cn", "citedby": 60, "publications": {"eZvfNC8AAAAJ:u-x6o8ySG0sC": {"container_type": "Publication", "source": "AUTHOR_PUBLICATION_ENTRY", "bib": {"title": "Simpledeepsearcher: Deep information seeking via web-powered reasoning trajectory synthesis", "pub_year": "2025"}, "filled": false, "author_pub_id": "eZvfNC8AAAAJ:u-x6o8ySG0sC", "num_citations": 39, "citedby_url": "https://scholar.google.com/scholar?oi=bibs&hl=en&cites=15362207412762137687,2782901356851532939", "cites_id": ["15362207412762137687", "2782901356851532939"]}, "eZvfNC8AAAAJ:u5HHmVD_uO8C": {"container_type": "Publication", "source": "AUTHOR_PUBLICATION_ENTRY", "bib": {"title": "STICKERCONV: Generating multimodal empathetic responses from scratch", "pub_year": "2024"}, "filled": false, "author_pub_id": "eZvfNC8AAAAJ:u5HHmVD_uO8C", "num_citations": 20, "citedby_url": "https://scholar.google.com/scholar?oi=bibs&hl=en&cites=13885741137843756184", "cites_id": ["13885741137843756184"]}, "eZvfNC8AAAAJ:qjMakFHDy7sC": {"container_type": "Publication", "source": "AUTHOR_PUBLICATION_ENTRY", "bib": {"title": "SWE-World: Building Software Engineering Agents in Docker-Free Environments", "pub_year": "2026"}, "filled": false, "author_pub_id": "eZvfNC8AAAAJ:qjMakFHDy7sC", "num_citations": 1, "citedby_url": "https://scholar.google.com/scholar?oi=bibs&hl=en&cites=17964542522173562021", "cites_id": ["17964542522173562021"]}, "eZvfNC8AAAAJ:2osOgNQ5qMEC": {"container_type": "Publication", "source": "AUTHOR_PUBLICATION_ENTRY", "bib": {"title": "SWE-Master: Unleashing the Potential of Software Engineering Agents via Post-Training", "pub_year": "2026"}, "filled": false, "author_pub_id": "eZvfNC8AAAAJ:2osOgNQ5qMEC", "num_citations": 0}}, "citedby5y": 60, "hindex": 2, "hindex5y": 2, "i10index": 2, "i10index5y": 2, "cites_per_year": {"2023": 1, "2024": 3, "2025": 52, "2026": 4}, "updated": "2026-02-17 08:49:35.123551"}